[
  {
    "name": "Soundtracks - Prologue",
    "category": "Museum",
    "intArgs": [
      0
    ],
    "strArgs": [
      "myElements",
      "\\11",
      "myData",
      "RewardMusic",
      "\\0",
      "myStatus"
    ],
    "widget": {
      "type": "list",
      "listItemNames": [
        "Locked",
        "Unlocked at world 1",
        "Unlocked at world 2",
        "Unlocked at world 3",
        "Unlocked at world 4"
      ],
      "listItemValues": [
        0.000000,
        1.000000,
        2.000000,
        3.000000,
        4.000000
      ]
    }
  },
  {
    "name": "Soundtracks - Grand Opening",
    "category": "Museum",
    "intArgs": [
      0
    ],
    "strArgs": [
      "myElements",
      "\\11",
      "myData",
      "RewardMusic",
      "\\1",
      "myStatus"
    ],
    "widget": {
      "type": "list",
      "listItemNames": [
        "Locked",
        "Unlocked at world 1",
        "Unlocked at world 2",
        "Unlocked at world 3",
        "Unlocked at world 4"
      ],
      "listItemValues": [
        0.000000,
        1.000000,
        2.000000,
        3.000000,
        4.000000
      ]
    }
  },
  {
    "name": "Soundtracks - Beep-O's Lesson",
    "category": "Museum",
    "intArgs": [
      0
    ],
    "strArgs": [
      "myElements",
      "\\11",
      "myData",
      "RewardMusic",
      "\\2",
      "myStatus"
    ],
    "widget": {
      "type": "list",
      "listItemNames": [
        "Locked",
        "Unlocked at world 1",
        "Unlocked at world 2",
        "Unlocked at world 3",
        "Unlocked at world 4"
      ],
      "listItemValues": [
        0.000000,
        1.000000,
        2.000000,
        3.000000,
        4.000000
      ]
    }
  },
  {
    "name": "Soundtracks - Ziggies Battle",
    "category": "Museum",
    "intArgs": [
      0
    ],
    "strArgs": [
      "myElements",
      "\\11",
      "myData",
      "RewardMusic",
      "\\3",
      "myStatus"
    ],
    "widget": {
      "type": "list",
      "listItemNames": [
        "Locked",
        "Unlocked at world 1",
        "Unlocked at world 2",
        "Unlocked at world 3",
        "Unlocked at world 4"
      ],
      "listItemValues": [
        0.000000,
        1.000000,
        2.000000,
        3.000000,
        4.000000
      ]
    }
  },

  {
    "name": "Soundtracks - The Waterfall Puzzle",
    "category": "Museum",
    "intArgs": [
      0
    ],
    "strArgs": [
      "myElements",
      "\\11",
      "myData",
      "RewardMusic",
      "\\4",
      "myStatus"
    ],
    "widget": {
      "type": "list",
      "listItemNames": [
        "Locked",
        "Unlocked at world 1",
        "Unlocked at world 2",
        "Unlocked at world 3",
        "Unlocked at world 4"
      ],
      "listItemValues": [
        0.000000,
        1.000000,
        2.000000,
        3.000000,
        4.000000
      ]
    }
  },
  {
    "name": "Soundtracks - A Towering View",
    "category": "Museum",
    "intArgs": [
      0
    ],
    "strArgs": [
      "myElements",
      "\\11",
      "myData",
      "RewardMusic",
      "\\5",
      "myStatus"
    ],
    "widget": {
      "type": "list",
      "listItemNames": [
        "Locked",
        "Unlocked at world 1",
        "Unlocked at world 2",
        "Unlocked at world 3",
        "Unlocked at world 4"
      ],
      "listItemValues": [
        0.000000,
        1.000000,
        2.000000,
        3.000000,
        4.000000
      ]
    }
  },
  {
    "name": "Soundtracks - Ancient Gardens",
    "category": "Museum",
    "intArgs": [
      0
    ],
    "strArgs": [
      "myElements",
      "\\11",
      "myData",
      "RewardMusic",
      "\\6",
      "myStatus"
    ],
    "widget": {
      "type": "list",
      "listItemNames": [
        "Locked",
        "Unlocked at world 1",
        "Unlocked at world 2",
        "Unlocked at world 3",
        "Unlocked at world 4"
      ],
      "listItemValues": [
        0.000000,
        1.000000,
        2.000000,
        3.000000,
        4.000000
      ]
    }
  },
  {
    "name": "Soundtracks - Through the Lawns",
    "category": "Museum",
    "intArgs": [
      0
    ],
    "strArgs": [
      "myElements",
      "\\11",
      "myData",
      "RewardMusic",
      "\\7",
      "myStatus"
    ],
    "widget": {
      "type": "list",
      "listItemNames": [
        "Locked",
        "Unlocked at world 1",
        "Unlocked at world 2",
        "Unlocked at world 3",
        "Unlocked at world 4"
      ],
      "listItemValues": [
        0.000000,
        1.000000,
        2.000000,
        3.000000,
        4.000000
      ]
    }
  },
  {
    "name": "Soundtracks - Mystic Journey",
    "category": "Museum",
    "intArgs": [
      0
    ],
    "strArgs": [
      "myElements",
      "\\11",
      "myData",
      "RewardMusic",
      "\\8",
      "myStatus"
    ],
    "widget": {
      "type": "list",
      "listItemNames": [
        "Locked",
        "Unlocked at world 1",
        "Unlocked at world 2",
        "Unlocked at world 3",
        "Unlocked at world 4"
      ],
      "listItemValues": [
        0.000000,
        1.000000,
        2.000000,
        3.000000,
        4.000000
      ]
    }
  },
  {
    "name": "Soundtracks - Mystic Battle",
    "category": "Museum",
    "intArgs": [
      0
    ],
    "strArgs": [
      "myElements",
      "\\11",
      "myData",
      "RewardMusic",
      "\\9",
      "myStatus"
    ],
    "widget": {
      "type": "list",
      "listItemNames": [
        "Locked",
        "Unlocked at world 1",
        "Unlocked at world 2",
        "Unlocked at world 3",
        "Unlocked at world 4"
      ],
      "listItemValues": [
        0.000000,
        1.000000,
        2.000000,
        3.000000,
        4.000000
      ]
    }
  },
  {
    "name": "Soundtracks - The Midboss Theme",
    "category": "Museum",
    "intArgs": [
      0
    ],
    "strArgs": [
      "myElements",
      "\\11",
      "myData",
      "RewardMusic",
      "\\10",
      "myStatus"
    ],
    "widget": {
      "type": "list",
      "listItemNames": [
        "Locked",
        "Unlocked at world 1",
        "Unlocked at world 2",
        "Unlocked at world 3",
        "Unlocked at world 4"
      ],
      "listItemValues": [
        0.000000,
        1.000000,
        2.000000,
        3.000000,
        4.000000
      ]
    }
  },
  {
    "name": "Soundtracks - Hoppers!",
    "category": "Museum",
    "intArgs": [
      0
    ],
    "strArgs": [
      "myElements",
      "\\11",
      "myData",
      "RewardMusic",
      "\\11",
      "myStatus"
    ],
    "widget": {
      "type": "list",
      "listItemNames": [
        "Locked",
        "Unlocked at world 1",
        "Unlocked at world 2",
        "Unlocked at world 3",
        "Unlocked at world 4"
      ],
      "listItemValues": [
        0.000000,
        1.000000,
        2.000000,
        3.000000,
        4.000000
      ]
    }
  },
  {
    "name": "Soundtracks - At the Towers Feet",
    "category": "Museum",
    "intArgs": [
      0
    ],
    "strArgs": [
      "myElements",
      "\\11",
      "myData",
      "RewardMusic",
      "\\12",
      "myStatus"
    ],
    "widget": {
      "type": "list",
      "listItemNames": [
        "Locked",
        "Unlocked at world 1",
        "Unlocked at world 2",
        "Unlocked at world 3",
        "Unlocked at world 4"
      ],
      "listItemValues": [
        0.000000,
        1.000000,
        2.000000,
        3.000000,
        4.000000
      ]
    }
  },
  {
    "name": "Soundtracks - Tower's Theme 1",
    "category": "Museum",
    "intArgs": [
      0
    ],
    "strArgs": [
      "myElements",
      "\\11",
      "myData",
      "RewardMusic",
      "\\13",
      "myStatus"
    ],
    "widget": {
      "type": "list",
      "listItemNames": [
        "Locked",
        "Unlocked at world 1",
        "Unlocked at world 2",
        "Unlocked at world 3",
        "Unlocked at world 4"
      ],
      "listItemValues": [
        0.000000,
        1.000000,
        2.000000,
        3.000000,
        4.000000
      ]
    }
  },
  {
    "name": "Soundtracks - Tower's Puzzle",
    "category": "Museum",
    "intArgs": [
      0
    ],
    "strArgs": [
      "myElements",
      "\\11",
      "myData",
      "RewardMusic",
      "\\14",
      "myStatus"
    ],
    "widget": {
      "type": "list",
      "listItemNames": [
        "Locked",
        "Unlocked at world 1",
        "Unlocked at world 2",
        "Unlocked at world 3",
        "Unlocked at world 4"
      ],
      "listItemValues": [
        0.000000,
        1.000000,
        2.000000,
        3.000000,
        4.000000
      ]
    }
  },
  {
    "name": "Soundtracks - Tower's Theme 2",
    "category": "Museum",
    "intArgs": [
      0
    ],
    "strArgs": [
      "myElements",
      "\\11",
      "myData",
      "RewardMusic",
      "\\15",
      "myStatus"
    ],
    "widget": {
      "type": "list",
      "listItemNames": [
        "Locked",
        "Unlocked at world 1",
        "Unlocked at world 2",
        "Unlocked at world 3",
        "Unlocked at world 4"
      ],
      "listItemValues": [
        0.000000,
        1.000000,
        2.000000,
        3.000000,
        4.000000
      ]
    }
  },
  {
    "name": "Soundtracks - Rabbid Kong's Theme",
    "category": "Museum",
    "intArgs": [
      0
    ],
    "strArgs": [
      "myElements",
      "\\11",
      "myData",
      "RewardMusic",
      "\\16",
      "myStatus"
    ],
    "widget": {
      "type": "list",
      "listItemNames": [
        "Locked",
        "Unlocked at world 1",
        "Unlocked at world 2",
        "Unlocked at world 3",
        "Unlocked at world 4"
      ],
      "listItemValues": [
        0.000000,
        1.000000,
        2.000000,
        3.000000,
        4.000000
      ]
    }
  },
  {
    "name": "Soundtracks - A Song of Ice and Desert",
    "category": "Museum",
    "intArgs": [
      0
    ],
    "strArgs": [
      "myElements",
      "\\11",
      "myData",
      "RewardMusic",
      "\\17",
      "myStatus"
    ],
    "widget": {
      "type": "list",
      "listItemNames": [
        "Locked",
        "Unlocked at world 1",
        "Unlocked at world 2",
        "Unlocked at world 3",
        "Unlocked at world 4"
      ],
      "listItemValues": [
        0.000000,
        1.000000,
        2.000000,
        3.000000,
        4.000000
      ]
    }
  },
  {
    "name": "Soundtracks - Ice of Sherbet Desert",
    "category": "Museum",
    "intArgs": [
      0
    ],
    "strArgs": [
      "myElements",
      "\\11",
      "myData",
      "RewardMusic",
      "\\18",
      "myStatus"
    ],
    "widget": {
      "type": "list",
      "listItemNames": [
        "Locked",
        "Unlocked at world 1",
        "Unlocked at world 2",
        "Unlocked at world 3",
        "Unlocked at world 4"
      ],
      "listItemValues": [
        0.000000,
        1.000000,
        2.000000,
        3.000000,
        4.000000
      ]
    }
  },
  {
    "name": "Soundtracks - In the Heat of the Battle",
    "category": "Museum",
    "intArgs": [
      0
    ],
    "strArgs": [
      "myElements",
      "\\11",
      "myData",
      "RewardMusic",
      "\\19",
      "myStatus"
    ],
    "widget": {
      "type": "list",
      "listItemNames": [
        "Locked",
        "Unlocked at world 1",
        "Unlocked at world 2",
        "Unlocked at world 3",
        "Unlocked at world 4"
      ],
      "listItemValues": [
        0.000000,
        1.000000,
        2.000000,
        3.000000,
        4.000000
      ]
    }
  },
  {
    "name": "Soundtracks - Hot Start, Cold Finish",
    "category": "Museum",
    "intArgs": [
      0
    ],
    "strArgs": [
      "myElements",
      "\\11",
      "myData",
      "RewardMusic",
      "\\20",
      "myStatus"
    ],
    "widget": {
      "type": "list",
      "listItemNames": [
        "Locked",
        "Unlocked at world 1",
        "Unlocked at world 2",
        "Unlocked at world 3",
        "Unlocked at world 4"
      ],
      "listItemValues": [
        0.000000,
        1.000000,
        2.000000,
        3.000000,
        4.000000
      ]
    }
  },
  {
    "name": "Soundtracks - Cold Start, Hot Finish",
    "category": "Museum",
    "intArgs": [
      0
    ],
    "strArgs": [
      "myElements",
      "\\11",
      "myData",
      "RewardMusic",
      "\\21",
      "myStatus"
    ],
    "widget": {
      "type": "list",
      "listItemNames": [
        "Locked",
        "Unlocked at world 1",
        "Unlocked at world 2",
        "Unlocked at world 3",
        "Unlocked at world 4"
      ],
      "listItemValues": [
        0.000000,
        1.000000,
        2.000000,
        3.000000,
        4.000000
      ]
    }
  },
  {
    "name": "Soundtracks - In the Cold of the Battle",
    "category": "Museum",
    "intArgs": [
      0
    ],
    "strArgs": [
      "myElements",
      "\\11",
      "myData",
      "RewardMusic",
      "\\22",
      "myStatus"
    ],
    "widget": {
      "type": "list",
      "listItemNames": [
        "Locked",
        "Unlocked at world 1",
        "Unlocked at world 2",
        "Unlocked at world 3",
        "Unlocked at world 4"
      ],
      "listItemValues": [
        0.000000,
        1.000000,
        2.000000,
        3.000000,
        4.000000
      ]
    }
  },
  {
    "name": "Soundtracks - Icicle Golem's Theme",
    "category": "Museum",
    "intArgs": [
      0
    ],
    "strArgs": [
      "myElements",
      "\\11",
      "myData",
      "RewardMusic",
      "\\23",
      "myStatus"
    ],
    "widget": {
      "type": "list",
      "listItemNames": [
        "Locked",
        "Unlocked at world 1",
        "Unlocked at world 2",
        "Unlocked at world 3",
        "Unlocked at world 4"
      ],
      "listItemValues": [
        0.000000,
        1.000000,
        2.000000,
        3.000000,
        4.000000
      ]
    }
  },

  {
    "name": "Soundtracks - Spooky Village",
    "category": "Museum",
    "intArgs": [
      0
    ],
    "strArgs": [
      "myElements",
      "\\11",
      "myData",
      "RewardMusic",
      "\\24",
      "myStatus"
    ],
    "widget": {
      "type": "list",
      "listItemNames": [
        "Locked",
        "Unlocked at world 1",
        "Unlocked at world 2",
        "Unlocked at world 3",
        "Unlocked at world 4"
      ],
      "listItemValues": [
        0.000000,
        1.000000,
        2.000000,
        3.000000,
        4.000000
      ]
    }
  },
  {
    "name": "Soundtracks - Spooky Skirmish",
    "category": "Museum",
    "intArgs": [
      0
    ],
    "strArgs": [
      "myElements",
      "\\11",
      "myData",
      "RewardMusic",
      "\\25",
      "myStatus"
    ],
    "widget": {
      "type": "list",
      "listItemNames": [
        "Locked",
        "Unlocked at world 1",
        "Unlocked at world 2",
        "Unlocked at world 3",
        "Unlocked at world 4"
      ],
      "listItemValues": [
        0.000000,
        1.000000,
        2.000000,
        3.000000,
        4.000000
      ]
    }
  },
  {
    "name": "Soundtracks - Abbey Ruins",
    "category": "Museum",
    "intArgs": [
      0
    ],
    "strArgs": [
      "myElements",
      "\\11",
      "myData",
      "RewardMusic",
      "\\26",
      "myStatus"
    ],
    "widget": {
      "type": "list",
      "listItemNames": [
        "Locked",
        "Unlocked at world 1",
        "Unlocked at world 2",
        "Unlocked at world 3",
        "Unlocked at world 4"
      ],
      "listItemValues": [
        0.000000,
        1.000000,
        2.000000,
        3.000000,
        4.000000
      ]
    }
  },
  {
    "name": "Soundtracks - Lost in the Swamp",
    "category": "Museum",
    "intArgs": [
      0
    ],
    "strArgs": [
      "myElements",
      "\\11",
      "myData",
      "RewardMusic",
      "\\27",
      "myStatus"
    ],
    "widget": {
      "type": "list",
      "listItemNames": [
        "Locked",
        "Unlocked at world 1",
        "Unlocked at world 2",
        "Unlocked at world 3",
        "Unlocked at world 4"
      ],
      "listItemValues": [
        0.000000,
        1.000000,
        2.000000,
        3.000000,
        4.000000
      ]
    }
  },
  {
    "name": "Soundtracks - The Swamp Battle",
    "category": "Museum",
    "intArgs": [
      0
    ],
    "strArgs": [
      "myElements",
      "\\11",
      "myData",
      "RewardMusic",
      "\\28",
      "myStatus"
    ],
    "widget": {
      "type": "list",
      "listItemNames": [
        "Locked",
        "Unlocked at world 1",
        "Unlocked at world 2",
        "Unlocked at world 3",
        "Unlocked at world 4"
      ],
      "listItemValues": [
        0.000000,
        1.000000,
        2.000000,
        3.000000,
        4.000000
      ]
    }
  },
  {
    "name": "Soundtracks - Combat in the Cemetery",
    "category": "Museum",
    "intArgs": [
      0
    ],
    "strArgs": [
      "myElements",
      "\\11",
      "myData",
      "RewardMusic",
      "\\29",
      "myStatus"
    ],
    "widget": {
      "type": "list",
      "listItemNames": [
        "Locked",
        "Unlocked at world 1",
        "Unlocked at world 2",
        "Unlocked at world 3",
        "Unlocked at world 4"
      ],
      "listItemValues": [
        0.000000,
        1.000000,
        2.000000,
        3.000000,
        4.000000
      ]
    }
  },
  {
    "name": "Soundtracks - A Stroll in the Cemetery",
    "category": "Museum",
    "intArgs": [
      0
    ],
    "strArgs": [
      "myElements",
      "\\11",
      "myData",
      "RewardMusic",
      "\\30",
      "myStatus"
    ],
    "widget": {
      "type": "list",
      "listItemNames": [
        "Locked",
        "Unlocked at world 1",
        "Unlocked at world 2",
        "Unlocked at world 3",
        "Unlocked at world 4"
      ],
      "listItemValues": [
        0.000000,
        1.000000,
        2.000000,
        3.000000,
        4.000000
      ]
    }
  },
  {
    "name": "Soundtracks - Phantom's Theme",
    "category": "Museum",
    "intArgs": [
      0
    ],
    "strArgs": [
      "myElements",
      "\\11",
      "myData",
      "RewardMusic",
      "\\31",
      "myStatus"
    ],
    "widget": {
      "type": "list",
      "listItemNames": [
        "Locked",
        "Unlocked at world 1",
        "Unlocked at world 2",
        "Unlocked at world 3",
        "Unlocked at world 4"
      ],
      "listItemValues": [
        0.000000,
        1.000000,
        2.000000,
        3.000000,
        4.000000
      ]
    }
  },
  {
    "name": "Soundtracks - Into the Pit",
    "category": "Museum",
    "intArgs": [
      0
    ],
    "strArgs": [
      "myElements",
      "\\11",
      "myData",
      "RewardMusic",
      "\\32",
      "myStatus"
    ],
    "widget": {
      "type": "list",
      "listItemNames": [
        "Locked",
        "Unlocked at world 1",
        "Unlocked at world 2",
        "Unlocked at world 3",
        "Unlocked at world 4"
      ],
      "listItemValues": [
        0.000000,
        1.000000,
        2.000000,
        3.000000,
        4.000000
      ]
    }
  },
  {
    "name": "Soundtracks - The Forge Battle",
    "category": "Museum",
    "intArgs": [
      0
    ],
    "strArgs": [
      "myElements",
      "\\11",
      "myData",
      "RewardMusic",
      "\\33",
      "myStatus"
    ],
    "widget": {
      "type": "list",
      "listItemNames": [
        "Locked",
        "Unlocked at world 1",
        "Unlocked at world 2",
        "Unlocked at world 3",
        "Unlocked at world 4"
      ],
      "listItemValues": [
        0.000000,
        1.000000,
        2.000000,
        3.000000,
        4.000000
      ]
    }
  },
  {
    "name": "Soundtracks - Exploring the Mine",
    "category": "Museum",
    "intArgs": [
      0
    ],
    "strArgs": [
      "myElements",
      "\\11",
      "myData",
      "RewardMusic",
      "\\34",
      "myStatus"
    ],
    "widget": {
      "type": "list",
      "listItemNames": [
        "Locked",
        "Unlocked at world 1",
        "Unlocked at world 2",
        "Unlocked at world 3",
        "Unlocked at world 4"
      ],
      "listItemValues": [
        0.000000,
        1.000000,
        2.000000,
        3.000000,
        4.000000
      ]
    }
  },
  {
    "name": "Soundtracks - Heart of Darkness",
    "category": "Museum",
    "intArgs": [
      0
    ],
    "strArgs": [
      "myElements",
      "\\11",
      "myData",
      "RewardMusic",
      "\\35",
      "myStatus"
    ],
    "widget": {
      "type": "list",
      "listItemNames": [
        "Locked",
        "Unlocked at world 1",
        "Unlocked at world 2",
        "Unlocked at world 3",
        "Unlocked at world 4"
      ],
      "listItemValues": [
        0.000000,
        1.000000,
        2.000000,
        3.000000,
        4.000000
      ]
    }
  },
  {
    "name": "Soundtracks - Theme with no Name 1",
    "category": "Museum",
    "intArgs": [
      0
    ],
    "strArgs": [
      "myElements",
      "\\11",
      "myData",
      "RewardMusic",
      "\\36",
      "myStatus"
    ],
    "widget": {
      "type": "list",
      "listItemNames": [
        "Locked",
        "Unlocked at world 1",
        "Unlocked at world 2",
        "Unlocked at world 3",
        "Unlocked at world 4"
      ],
      "listItemValues": [
        0.000000,
        1.000000,
        2.000000,
        3.000000,
        4.000000
      ]
    }
  },
  {
    "name": "Soundtracks - Theme with no Name 2",
    "category": "Museum",
    "intArgs": [
      0
    ],
    "strArgs": [
      "myElements",
      "\\11",
      "myData",
      "RewardMusic",
      "\\37",
      "myStatus"
    ],
    "widget": {
      "type": "list",
      "listItemNames": [
        "Locked",
        "Unlocked at world 1",
        "Unlocked at world 2",
        "Unlocked at world 3",
        "Unlocked at world 4"
      ],
      "listItemValues": [
        0.000000,
        1.000000,
        2.000000,
        3.000000,
        4.000000
      ]
    }
  },
  {
    "name": "Soundtracks - Theme with no Name 3",
    "category": "Museum",
    "intArgs": [
      0
    ],
    "strArgs": [
      "myElements",
      "\\11",
      "myData",
      "RewardMusic",
      "\\38",
      "myStatus"
    ],
    "widget": {
      "type": "list",
      "listItemNames": [
        "Locked",
        "Unlocked at world 1",
        "Unlocked at world 2",
        "Unlocked at world 3",
        "Unlocked at world 4"
      ],
      "listItemValues": [
        0.000000,
        1.000000,
        2.000000,
        3.000000,
        4.000000
      ]
    }
  },
  {
    "name": "Soundtracks - Bowser's theme",
    "category": "Museum",
    "intArgs": [
      0
    ],
    "strArgs": [
      "myElements",
      "\\11",
      "myData",
      "RewardMusic",
      "\\39",
      "myStatus"
    ],
    "widget": {
      "type": "list",
      "listItemNames": [
        "Locked",
        "Unlocked at world 1",
        "Unlocked at world 2",
        "Unlocked at world 3",
        "Unlocked at world 4"
      ],
      "listItemValues": [
        0.000000,
        1.000000,
        2.000000,
        3.000000,
        4.000000
      ]
    }
  }
]
